{
  "db_name": "PostgreSQL",
  "query": "SELECT key, path FROM archives WHERE id = $1",
  "describe": {
    "columns": [
      {
        "ordinal": 0,
        "name": "key",
        "type_info": "Varchar"
      },
      {
        "ordinal": 1,
        "name": "path",
        "type_info": "Text"
      }
    ],
    "parameters": {
      "Left": [
        "Int8"
      ]
    },
    "nullable": [
      false,
      false
    ]
  },
  "hash": "1efbefad942884ac84836d20f878ed475c8a4ffd6caef09d11c8c3cb54ec530b"
}
