{
  "db_name": "PostgreSQL",
  "query": "SELECT name, url FROM archive_sources WHERE archive_id = $1 ORDER BY name ASC",
  "describe": {
    "columns": [
      {
        "ordinal": 0,
        "name": "name",
        "type_info": "Varchar"
      },
      {
        "ordinal": 1,
        "name": "url",
        "type_info": "Varchar"
      }
    ],
    "parameters": {
      "Left": [
        "Int8"
      ]
    },
    "nullable": [
      false,
      true
    ]
  },
  "hash": "06c7003aa04377f852690b547167b0e7dc56f2495345c4c7bb99f358b8aafe3f"
}
